djay/.gitignore
djay/__init__.py
djay/addon.py
djay/application.py
djay/blueprint.py
djay/blueprints/__init__.py
djay/blueprints/command/__init__.py
djay/blueprints/command/context.py
djay/blueprints/command/templates/{{app}}/__init__.py.j2
djay/blueprints/command/templates/{{app}}/management/__init__.py.j2
djay/blueprints/command/templates/{{app}}/management/commands/__init__.py.j2
djay/blueprints/command/templates/{{app}}/management/commands/{{name}}.py
djay/blueprints/init/__init__.py
djay/blueprints/init/context.py
djay/blueprints/init/templates/LICENSE.md
djay/blueprints/init/templates/MANIFEST.in
djay/blueprints/init/templates/README.md
djay/blueprints/init/templates/manage.py.j2
djay/blueprints/init/templates/requirements.txt
djay/blueprints/init/templates/requirements.txt.dev
djay/blueprints/init/templates/setup.py.j2
djay/blueprints/init/templates/tests/__init__.py.j2
djay/blueprints/init/templates/tests/settings.py.j2
djay/blueprints/init/templates/{{app}}/__init__.py.j2
djay/blueprints/init/templates/{{app}}/admin.py.j2
djay/blueprints/init/templates/{{app}}/apps.py.j2
djay/blueprints/init/templates/{{app}}/management/__init__.py.j2
djay/blueprints/init/templates/{{app}}/management/commands/__init__.py.j2
djay/blueprints/init/templates/{{app}}/migrations/__init__.py.j2
djay/blueprints/init/templates/{{app}}/models/__init__.py.j2
djay/blueprints/init/templates/{{app}}/settings.py.j2
djay/blueprints/init/templates/{{app}}/urls.py.j2
djay/blueprints/init/templates/{{app}}/utils/__init__.py.j2
djay/blueprints/init/templates/{{app}}/wsgi.py.j2
djay/blueprints/model/__init__.py
djay/blueprints/model/context.py
djay/blueprints/model/templates/tests/__init__.py.j2
djay/blueprints/model/templates/tests/unit/__init__.py.j2
djay/blueprints/model/templates/tests/unit/models/test_{{name}}.py.j2
djay/blueprints/model/templates/{{app}}/models/__init__.py.j2
djay/blueprints/model/templates/{{app}}/models/base.py.j2
djay-0.0.9.dist-info/LICENSE
djay-0.0.9.dist-info/LICENSE.md
djay-0.0.9.dist-info/WHEEL
djay-0.0.9.dist-info/METADATA
djay-0.0.9.dist-info/RECORD
