Metadata-Version: 2.1
Name: djay
Version: 0.0.9
Summary: The advanced Django CLI
License: MIT
Author: aleontiev
Author-email: alonetiev@gmail.com
Requires-Python: >=3.6,<4.0
Classifier: License :: OSI Approved :: MIT License
Classifier: Programming Language :: Python :: 3
Classifier: Programming Language :: Python :: 3.6
Classifier: Programming Language :: Python :: 3.7
Classifier: Programming Language :: Python :: 3.8
Requires-Dist: click
Requires-Dist: flake8
Requires-Dist: inflection
Requires-Dist: jinja2
Requires-Dist: pyyaml
Requires-Dist: redbaron
Requires-Dist: six
